django_simple_account/__init__.py
django_simple_account/admin.py
django_simple_account/apps.py
django_simple_account/context_processors.py
django_simple_account/converters.py
django_simple_account/forms.py
django_simple_account/models.py
django_simple_account/signals.py
django_simple_account/urls.py
django_simple_account/validators.py
django_simple_account/views.py
django_simple_account/locale/ru/LC_MESSAGES/django.po
django_simple_account/management/__init__.py
django_simple_account/management/commands/__init__.py
django_simple_account/management/commands/compilemessages.py
django_simple_account/management/commands/makemessages.py
django_simple_account/migrations/0001_initial.py
django_simple_account/migrations/__init__.py
django_simple_account/static/django_simple_account/assets/css/login.css
django_simple_account/static/django_simple_account/assets/images/blur.jpg
django_simple_account/static/django_simple_account/assets/images/login.jpg
django_simple_account/static/django_simple_account/assets/images/logo.svg
django_simple_account/templates/django_simple_account/blank.html
django_simple_account/templates/django_simple_account/common.html
django_simple_account/templates/django_simple_account/forgot_password.html
django_simple_account/templates/django_simple_account/forgot_password_confirmation.html
django_simple_account/templates/django_simple_account/login.html
django_simple_account/templates/django_simple_account/oauth_completion.html
django_simple_account/templates/django_simple_account/oauth_facebook.html
django_simple_account/templates/django_simple_account/oauth_google.html
django_simple_account/templates/django_simple_account/signup.html
django_simple_account/templates/django_simple_account/email/forgotpassword.body.html
django_simple_account/templates/django_simple_account/email/forgotpassword.body.txt
django_simple_account/templates/django_simple_account/email/forgotpassword.subject.txt
django_simple_account-0.0.18.dist-info/LICENSE
django_simple_account-0.0.18.dist-info/METADATA
django_simple_account-0.0.18.dist-info/WHEEL
django_simple_account-0.0.18.dist-info/top_level.txt
django_simple_account-0.0.18.dist-info/RECORD
